markout_html/__init__.py
markout_html/cli.py
markout_html/extract.py
markout_html/markout_html.py
markout_html-0.1.7.dist-info/LICENSE
markout_html-0.1.7.dist-info/METADATA
markout_html-0.1.7.dist-info/WHEEL
markout_html-0.1.7.dist-info/entry_points.txt
markout_html-0.1.7.dist-info/top_level.txt
markout_html-0.1.7.dist-info/RECORD
