Metadata-Version: 2.1
Name: markout-html
Version: 0.1.7
Summary: A small Python package to extract content from web pages.
Home-page: https://github.com/oAGoulart/markout
Author: Augusto Goulart
Author-email: josegoulart.aluno@unipampa.edu.br
License: UNKNOWN
Project-URL: Bug Reports, https://github.com/oAGoulart/markout/issues
Project-URL: Source, https://github.com/oAGoulart/markout
Keywords: html conversion markup
Platform: UNKNOWN
Classifier: Development Status :: 5 - Production/Stable
Classifier: Intended Audience :: Developers
Classifier: Topic :: Text Processing :: Markup :: HTML
Classifier: License :: OSI Approved :: MIT License
Classifier: Programming Language :: Python :: 3
Requires-Python: >=3.5
Requires-Dist: pyquery (>=1.3)
